pongrid/__init__.py
pongrid/pongrid.py
pongrid/data/mystyle.mplstyle
pongrid-0.0.1.dist-info/LICENSE
pongrid-0.0.1.dist-info/METADATA
pongrid-0.0.1.dist-info/WHEEL
pongrid-0.0.1.dist-info/top_level.txt
pongrid-0.0.1.dist-info/RECORD
