Metadata-Version: 2.1
Name: pongrid
Version: 0.0.1
Summary: simple tool for computing probability on parameter grid and visualization
Home-page: https://github.com/sarashenyy/PonGrid
Author: Yueyue Shen
Author-email: shenyy@nao.cas.cn
License: MIT
License-File: LICENSE
Requires-Dist: numpy
Requires-Dist: scipy
Requires-Dist: tqdm
Requires-Dist: matplotlib >=3.7.2
Requires-Dist: seaborn
